odoo/addons/edi_voxel_secondary_unit_oca/README.rst
odoo/addons/edi_voxel_secondary_unit_oca/__init__.py
odoo/addons/edi_voxel_secondary_unit_oca/__manifest__.py
odoo/addons/edi_voxel_secondary_unit_oca/i18n/edi_voxel_secondary_unit.pot
odoo/addons/edi_voxel_secondary_unit_oca/i18n/edi_voxel_secondary_unit_oca.pot
odoo/addons/edi_voxel_secondary_unit_oca/i18n/es.po
odoo/addons/edi_voxel_secondary_unit_oca/i18n/it.po
odoo/addons/edi_voxel_secondary_unit_oca/models/__init__.py
odoo/addons/edi_voxel_secondary_unit_oca/models/product_secondary_unit.py
odoo/addons/edi_voxel_secondary_unit_oca/readme/CONTRIBUTORS.md
odoo/addons/edi_voxel_secondary_unit_oca/readme/DESCRIPTION.md
odoo/addons/edi_voxel_secondary_unit_oca/readme/USAGE.md
odoo/addons/edi_voxel_secondary_unit_oca/static/description/icon.png
odoo/addons/edi_voxel_secondary_unit_oca/static/description/index.html
odoo/addons/edi_voxel_secondary_unit_oca/views/product_secondary_unit_views.xml
odoo_addon_edi_voxel_secondary_unit_oca-18.0.1.0.0.4.dist-info/METADATA
odoo_addon_edi_voxel_secondary_unit_oca-18.0.1.0.0.4.dist-info/WHEEL
odoo_addon_edi_voxel_secondary_unit_oca-18.0.1.0.0.4.dist-info/top_level.txt
odoo_addon_edi_voxel_secondary_unit_oca-18.0.1.0.0.4.dist-info/RECORD
